{"startdate":"20220406","fullstartdate":"202204061600","enddate":"20220407","url":"https://www.bing.com/th?id=OHR.Malaga_ZH-CN9644862917_1920x1080.jpg&rf=LaDigue_1920x1080.jpg&pid=hp","urlbase":"https://www.bing.com/th?id=OHR.Malaga_ZH-CN9644862917","copyright":"黄昏下的马拉加老城，西班牙 (© Sean Pavone Photo/Getty Images)","copyrightlink":"https://www.bing.com/search?q=%E9%A9%AC%E6%8B%89%E5%8A%A0&form=hpcapt&mkt=zh-cn","title":"2800年历史的老城","quiz":"https://www.bing.com/search?q=Bing+homepage+quiz&filters=WQOskey:%22HPQuiz_20220406_Malaga%22&FORM=HPQUIZ","wp":true,"hsh":"f0bbc90132f665c909046005519d98ed","drk":1,"top":1,"bot":1,"hs":[]}