{"startdate":"20240920","fullstartdate":"202409202300","enddate":"20240921","url":"https://www.bing.com/th?id=OHR.MunichBeerfest_EN-GB0671591824_1920x1080.jpg&rf=LaDigue_1920x1080.jpg&pid=hp","urlbase":"https://www.bing.com/th?id=OHR.MunichBeerfest_EN-GB0671591824","copyright":"Oktoberfest in Munich from a high view at sunset (© AllesSuper21/iStock/Getty Images)","copyrightlink":"https://www.bing.com/search?q=oktoberfest&form=hpcapt&filters=HpDate%3a%2220240920_2300%22","title":"Prost to Oktoberfest!","quiz":"https://www.bing.com/search?q=Bing+homepage+quiz&filters=WQOskey:%22HPQuiz_20240920_MunichBeerfest%22&FORM=HPQUIZ","wp":true,"hsh":"0d8d9d04eda7876748ef9d0f4c6e9334","drk":1,"top":1,"bot":1,"hs":[]}