{"startdate":"20220619","fullstartdate":"202206191600","enddate":"20220620","url":"https://www.bing.com/th?id=OHR.SwallowtailFlower_ZH-CN5950463168_1920x1080.jpg&rf=LaDigue_1920x1080.jpg&pid=hp","urlbase":"https://www.bing.com/th?id=OHR.SwallowtailFlower_ZH-CN5950463168","copyright":"停在同一朵花上的两只金凤蝶 (© Alberto Ghizzi Panizza/Getty Images)","copyrightlink":"https://www.bing.com/search?q=%E9%87%91%E5%87%A4%E8%9D%B6&form=hpcapt&mkt=zh-cn","title":"一起吃午饭吗?","quiz":"https://www.bing.com/search?q=Bing+homepage+quiz&filters=WQOskey:%22HPQuiz_20220619_SwallowtailFlower%22&FORM=HPQUIZ","wp":true,"hsh":"dfa0e77da6dfbb2283cd39fa2cae9693","drk":1,"top":1,"bot":1,"hs":[]}